{
  "locations": [
    {
      "id": "jhb",
      "name": "JHB Office",
      "capacity": 21,
      "address": "22 Cradock Ave, Rosebank, Sandton, 2196"
    },
    {
      "id": "cpt",
      "name": "Cape Town Office",
      "capacity": 15,
      "address": "34 Bree St, Cape Town City Centre, Cape Town, 8001"
    }
  ],
  "teams": [
    {
      "id": "hello",
      "name": "Migrations",
      "manager": "Koos Kombuis",
      "managerImage": "https://cdn.24.co.za/files/Cms/General/d/11988/10165fab227f49959d704211cc2dbd28.jpg",
      "color": "#3b82f6",
      "memberCount": 6,
      "locationId": "jhb"
    },
    {
      "id": "absa-cib",
      "name": "ABSA CIB",
      "manager": "Hugo Lindeque",
      "managerImage": "https://cdn.prod.website-files.com/66cd7e92bafc89dd93fa816b/671241eb3b22dfce4de76662_Hugo%20Lindeque.avif",
      "color": "#ff7e79",
      "memberCount": 5,
      "locationId": "jhb"
    },
    {
      "id": "c-suite",
      "name": "C-Suite",
      "manager": "Nemanja Stabic",
      "managerImage": "https://cdn.prod.website-files.com/66cd7e92bafc89dd93fa816b/66e0560d392f89eb4d3bff0b_Nem.avif",
      "color": "#ff6a00",
      "memberCount": 4,
      "locationId": "jhb"
    }
  ],
  "bookings": [
    {
      "id": "1765545452373",
      "date": "2025-12-16",
      "teamId": "hello",
      "teamName": "Hello",
      "peopleCount": 1,
      "locationId": "jhb",
      "notes": "",
      "createdAt": "2025-12-12T13:17:32.373Z"
    },
    {
      "id": "1765545564379",
      "date": "2025-12-25",
      "teamId": "hello",
      "teamName": "Migration",
      "peopleCount": 5,
      "locationId": "jhb",
      "notes": "",
      "createdAt": "2025-12-12T13:19:24.379Z"
    },
    {
      "id": "1765546059335",
      "date": "2025-12-19",
      "teamId": "absa-cib",
      "teamName": "ABSA CIB",
      "peopleCount": 1,
      "locationId": "jhb",
      "notes": "",
      "createdAt": "2025-12-12T13:27:39.335Z"
    },
    {
      "id": "1765546151676",
      "date": "2025-12-18",
      "teamId": "c-suite",
      "teamName": "C-Suite",
      "peopleCount": 4,
      "locationId": "jhb",
      "notes": "Testing",
      "createdAt": "2025-12-12T13:29:11.676Z"
    }
  ],
  "publicHolidays": [
    {
      "date": "2026-01-01",
      "name": "New Year's Day"
    },
    {
      "date": "2026-03-21",
      "name": "Human Rights Day"
    },
    {
      "date": "2026-04-03",
      "name": "Good Friday"
    },
    {
      "date": "2026-04-06",
      "name": "Family Day"
    },
    {
      "date": "2026-04-27",
      "name": "Freedom Day"
    },
    {
      "date": "2026-05-01",
      "name": "Workers' Day"
    },
    {
      "date": "2026-06-16",
      "name": "Youth Day"
    },
    {
      "date": "2026-08-10",
      "name": "National Women's Day"
    },
    {
      "date": "2026-09-24",
      "name": "Heritage Day"
    },
    {
      "date": "2026-12-16",
      "name": "Day of Reconciliation"
    },
    {
      "date": "2026-12-25",
      "name": "Christmas Day"
    },
    {
      "date": "2026-12-26",
      "name": "Day of Goodwill"
    }
  ],
  "desks": [
    {
      "id": "1765561922945",
      "name": "A1",
      "locationId": "jhb",
      "floor": "1st",
      "zone": "Main",
      "qrCode": "1765561922945-8rnoafo9l",
      "createdAt": "2025-12-12T17:52:02.945Z",
      "x": 160,
      "y": 400
    },
    {
      "id": "1765562899114",
      "name": "A2",
      "locationId": "jhb",
      "floor": "1st",
      "zone": "Main",
      "qrCode": "1765562899114-nhtdeyl4x",
      "createdAt": "2025-12-12T18:08:19.114Z",
      "x": 0,
      "y": 400
    },
    {
      "id": "1765564870668",
      "name": "C-01",
      "locationId": "jhb",
      "floor": "1",
      "zone": "",
      "x": 340,
      "y": 30,
      "width": 50,
      "height": 20,
      "deskType": "hotseat",
      "assignedTeamId": null,
      "chairPositions": [
        "top"
      ],
      "qrCode": "1765564870668-hgc6jkvew",
      "createdAt": "2025-12-12T18:41:10.668Z"
    },
    {
      "id": "1765564919089",
      "name": "C-02",
      "locationId": "jhb",
      "floor": "1",
      "zone": "",
      "x": 340,
      "y": 50,
      "width": 50,
      "height": 20,
      "deskType": "hotseat",
      "assignedTeamId": null,
      "chairPositions": [
        "bottom"
      ],
      "qrCode": "1765564919089-jvlv35l93",
      "createdAt": "2025-12-12T18:41:59.089Z"
    },
    {
      "id": "1765564984225",
      "name": "C-03",
      "locationId": "jhb",
      "floor": "1",
      "zone": "",
      "x": 390,
      "y": 50,
      "width": 50,
      "height": 20,
      "deskType": "hotseat",
      "assignedTeamId": null,
      "chairPositions": [
        "bottom"
      ],
      "qrCode": "1765564984225-xj717s4ag",
      "createdAt": "2025-12-12T18:43:04.225Z"
    },
    {
      "id": "1765565004994",
      "name": "C-04",
      "locationId": "jhb",
      "floor": "1",
      "zone": "",
      "x": 390,
      "y": 30,
      "width": 50,
      "height": 20,
      "deskType": "hotseat",
      "assignedTeamId": null,
      "chairPositions": [
        "top"
      ],
      "qrCode": "1765565004994-fd6x87p6r",
      "createdAt": "2025-12-12T18:43:24.994Z"
    },
    {
      "id": "1765565073508",
      "name": "A01",
      "locationId": "jhb",
      "floor": "1",
      "zone": "",
      "x": 0,
      "y": 460,
      "width": 50,
      "height": 20,
      "deskType": "hotseat",
      "assignedTeamId": null,
      "chairPositions": [
        "bottom"
      ],
      "qrCode": "1765565073508-xt3i5m039",
      "createdAt": "2025-12-12T18:44:33.508Z"
    },
    {
      "id": "1765565101693",
      "name": "A02",
      "locationId": "jhb",
      "floor": "1",
      "zone": "",
      "x": 50,
      "y": 460,
      "width": 50,
      "height": 20,
      "deskType": "hotseat",
      "assignedTeamId": null,
      "chairPositions": [
        "bottom"
      ],
      "qrCode": "1765565101693-cpsepvw0y",
      "createdAt": "2025-12-12T18:45:01.693Z"
    },
    {
      "id": "1765565119313",
      "name": "A03",
      "locationId": "jhb",
      "floor": "1",
      "zone": "",
      "x": 100,
      "y": 460,
      "width": 50,
      "height": 20,
      "deskType": "hotseat",
      "assignedTeamId": null,
      "chairPositions": [
        "bottom"
      ],
      "qrCode": "1765565119314-iw2uxc4bx",
      "createdAt": "2025-12-12T18:45:19.314Z"
    },
    {
      "id": "1765565133288",
      "name": "A04",
      "locationId": "jhb",
      "floor": "1",
      "zone": "",
      "x": 150,
      "y": 460,
      "width": 50,
      "height": 20,
      "deskType": "hotseat",
      "assignedTeamId": null,
      "chairPositions": [
        "bottom"
      ],
      "qrCode": "1765565133288-kwjzacx52",
      "createdAt": "2025-12-12T18:45:33.288Z"
    },
    {
      "id": "1765565152106",
      "name": "A09",
      "locationId": "jhb",
      "floor": "1",
      "zone": "",
      "x": 0,
      "y": 360,
      "width": 50,
      "height": 20,
      "deskType": "hotseat",
      "assignedTeamId": null,
      "chairPositions": [
        "bottom"
      ],
      "qrCode": "1765565152106-z2bgy8mqh",
      "createdAt": "2025-12-12T18:45:52.106Z"
    },
    {
      "id": "1765565206999",
      "name": "A10",
      "locationId": "jhb",
      "floor": "1",
      "zone": "",
      "x": 50,
      "y": 360,
      "width": 50,
      "height": 20,
      "deskType": "hotseat",
      "assignedTeamId": null,
      "chairPositions": [
        "bottom"
      ],
      "qrCode": "1765565206999-2zy3a7ca8",
      "createdAt": "2025-12-12T18:46:46.999Z"
    },
    {
      "id": "1765565221396",
      "name": "A11",
      "locationId": "jhb",
      "floor": "1",
      "zone": "",
      "x": 100,
      "y": 360,
      "width": 50,
      "height": 20,
      "deskType": "hotseat",
      "assignedTeamId": null,
      "chairPositions": [
        "bottom"
      ],
      "qrCode": "1765565221397-93bpsncbr",
      "createdAt": "2025-12-12T18:47:01.397Z"
    },
    {
      "id": "1765565234805",
      "name": "A12",
      "locationId": "jhb",
      "floor": "1",
      "zone": "",
      "x": 150,
      "y": 360,
      "width": 50,
      "height": 20,
      "deskType": "hotseat",
      "assignedTeamId": null,
      "chairPositions": [
        "bottom"
      ],
      "qrCode": "1765565234805-aitrd6f33",
      "createdAt": "2025-12-12T18:47:14.805Z"
    },
    {
      "id": "1765565256518",
      "name": "A17",
      "locationId": "jhb",
      "floor": "1",
      "zone": "",
      "x": 0,
      "y": 260,
      "width": 50,
      "height": 20,
      "deskType": "hotseat",
      "assignedTeamId": null,
      "chairPositions": [
        "bottom"
      ],
      "qrCode": "1765565256518-dar69xkbz",
      "createdAt": "2025-12-12T18:47:36.518Z"
    },
    {
      "id": "1765565276880",
      "name": "A18",
      "locationId": "jhb",
      "floor": "1",
      "zone": "",
      "x": 50,
      "y": 260,
      "width": 50,
      "height": 20,
      "deskType": "hotseat",
      "assignedTeamId": null,
      "chairPositions": [
        "bottom"
      ],
      "qrCode": "1765565276880-uplmg5t1w",
      "createdAt": "2025-12-12T18:47:56.880Z"
    },
    {
      "id": "1765565289163",
      "name": "A19",
      "locationId": "jhb",
      "floor": "1",
      "zone": "",
      "x": 100,
      "y": 260,
      "width": 50,
      "height": 20,
      "deskType": "hotseat",
      "assignedTeamId": null,
      "chairPositions": [
        "bottom"
      ],
      "qrCode": "1765565289163-xqhf4nivx",
      "createdAt": "2025-12-12T18:48:09.163Z"
    },
    {
      "id": "1765565307187",
      "name": "A20",
      "locationId": "jhb",
      "floor": "1",
      "zone": "",
      "x": 150,
      "y": 260,
      "width": 50,
      "height": 20,
      "deskType": "hotseat",
      "assignedTeamId": null,
      "chairPositions": [
        "bottom"
      ],
      "qrCode": "1765565307187-lo6oygetc",
      "createdAt": "2025-12-12T18:48:27.187Z"
    },
    {
      "id": "1765565370888",
      "name": "Boardroom",
      "locationId": "jhb",
      "floor": "1",
      "zone": "",
      "x": 60,
      "y": 50,
      "width": 80,
      "height": 60,
      "deskType": "hotseat",
      "assignedTeamId": null,
      "chairPositions": [
        "top",
        "bottom",
        "left",
        "right"
      ],
      "qrCode": "1765565370888-rf36ebpx2",
      "createdAt": "2025-12-12T18:49:30.888Z"
    },
    {
      "id": "1765565430495",
      "name": "A05",
      "locationId": "jhb",
      "floor": "1",
      "zone": "",
      "x": 0,
      "y": 440,
      "width": 50,
      "height": 20,
      "deskType": "hotseat",
      "assignedTeamId": null,
      "chairPositions": [
        "top"
      ],
      "qrCode": "1765565430495-wd153x96q",
      "createdAt": "2025-12-12T18:50:30.495Z"
    },
    {
      "id": "1765565505604",
      "name": "A06",
      "locationId": "jhb",
      "floor": "1",
      "zone": "",
      "x": 50,
      "y": 440,
      "width": 50,
      "height": 20,
      "deskType": "hotseat",
      "assignedTeamId": null,
      "chairPositions": [
        "top"
      ],
      "qrCode": "1765565505604-7bdee3sxi",
      "createdAt": "2025-12-12T18:51:45.604Z"
    },
    {
      "id": "1765565527988",
      "name": "A07",
      "locationId": "jhb",
      "floor": "1",
      "zone": "",
      "x": 100,
      "y": 440,
      "width": 50,
      "height": 20,
      "deskType": "hotseat",
      "assignedTeamId": null,
      "chairPositions": [
        "top"
      ],
      "qrCode": "1765565527988-ydkrmq1b6",
      "createdAt": "2025-12-12T18:52:07.988Z"
    },
    {
      "id": "1765565551477",
      "name": "A08",
      "locationId": "jhb",
      "floor": "1",
      "zone": "",
      "x": 150,
      "y": 440,
      "width": 50,
      "height": 20,
      "deskType": "hotseat",
      "assignedTeamId": null,
      "chairPositions": [
        "top"
      ],
      "qrCode": "1765565551477-cphv97khw",
      "createdAt": "2025-12-12T18:52:31.477Z"
    }
  ],
  "deskBookings": [
    {
      "id": "1765562268459",
      "deskId": "1765561922945",
      "deskName": "A1",
      "locationId": "jhb",
      "date": "2025-12-15",
      "startTime": "08:00",
      "endTime": "08:30",
      "employeeName": "Hugo",
      "employeeEmail": "",
      "checkedIn": false,
      "checkedInAt": null,
      "createdAt": "2025-12-12T17:57:48.459Z"
    },
    {
      "id": "1765562268464",
      "deskId": "1765561922945",
      "deskName": "A1",
      "locationId": "jhb",
      "date": "2025-12-15",
      "startTime": "08:30",
      "endTime": "09:00",
      "employeeName": "Hugo",
      "employeeEmail": "",
      "checkedIn": false,
      "checkedInAt": null,
      "createdAt": "2025-12-12T17:57:48.464Z"
    },
    {
      "id": "1765562268468",
      "deskId": "1765561922945",
      "deskName": "A1",
      "locationId": "jhb",
      "date": "2025-12-15",
      "startTime": "09:00",
      "endTime": "09:30",
      "employeeName": "Hugo",
      "employeeEmail": "",
      "checkedIn": false,
      "checkedInAt": null,
      "createdAt": "2025-12-12T17:57:48.468Z"
    },
    {
      "id": "1765562268472",
      "deskId": "1765561922945",
      "deskName": "A1",
      "locationId": "jhb",
      "date": "2025-12-15",
      "startTime": "09:30",
      "endTime": "10:00",
      "employeeName": "Hugo",
      "employeeEmail": "",
      "checkedIn": false,
      "checkedInAt": null,
      "createdAt": "2025-12-12T17:57:48.472Z"
    },
    {
      "id": "1765562268475",
      "deskId": "1765561922945",
      "deskName": "A1",
      "locationId": "jhb",
      "date": "2025-12-15",
      "startTime": "10:00",
      "endTime": "10:30",
      "employeeName": "Hugo",
      "employeeEmail": "",
      "checkedIn": false,
      "checkedInAt": null,
      "createdAt": "2025-12-12T17:57:48.475Z"
    },
    {
      "id": "1765562268479",
      "deskId": "1765561922945",
      "deskName": "A1",
      "locationId": "jhb",
      "date": "2025-12-15",
      "startTime": "10:30",
      "endTime": "11:00",
      "employeeName": "Hugo",
      "employeeEmail": "",
      "checkedIn": false,
      "checkedInAt": null,
      "createdAt": "2025-12-12T17:57:48.479Z"
    },
    {
      "id": "1765562268482",
      "deskId": "1765561922945",
      "deskName": "A1",
      "locationId": "jhb",
      "date": "2025-12-15",
      "startTime": "11:00",
      "endTime": "11:30",
      "employeeName": "Hugo",
      "employeeEmail": "",
      "checkedIn": false,
      "checkedInAt": null,
      "createdAt": "2025-12-12T17:57:48.482Z"
    },
    {
      "id": "1765562268486",
      "deskId": "1765561922945",
      "deskName": "A1",
      "locationId": "jhb",
      "date": "2025-12-15",
      "startTime": "11:30",
      "endTime": "12:00",
      "employeeName": "Hugo",
      "employeeEmail": "",
      "checkedIn": false,
      "checkedInAt": null,
      "createdAt": "2025-12-12T17:57:48.486Z"
    },
    {
      "id": "1765562400934",
      "deskId": "1765561922945",
      "deskName": "A1",
      "locationId": "jhb",
      "date": "2025-12-15",
      "startTime": "12:00",
      "endTime": "12:30",
      "employeeName": "Inge",
      "employeeEmail": "",
      "checkedIn": false,
      "checkedInAt": null,
      "createdAt": "2025-12-12T18:00:00.934Z"
    },
    {
      "id": "1765562400939",
      "deskId": "1765561922945",
      "deskName": "A1",
      "locationId": "jhb",
      "date": "2025-12-15",
      "startTime": "12:30",
      "endTime": "13:00",
      "employeeName": "Inge",
      "employeeEmail": "",
      "checkedIn": false,
      "checkedInAt": null,
      "createdAt": "2025-12-12T18:00:00.939Z"
    },
    {
      "id": "1765562400943",
      "deskId": "1765561922945",
      "deskName": "A1",
      "locationId": "jhb",
      "date": "2025-12-15",
      "startTime": "13:00",
      "endTime": "13:30",
      "employeeName": "Inge",
      "employeeEmail": "",
      "checkedIn": false,
      "checkedInAt": null,
      "createdAt": "2025-12-12T18:00:00.943Z"
    },
    {
      "id": "1765562565499",
      "deskId": "1765561922945",
      "deskName": "A1",
      "locationId": "jhb",
      "date": "2025-12-12",
      "startTime": "08:00",
      "endTime": "08:30",
      "employeeName": "Hugo",
      "employeeEmail": "",
      "checkedIn": false,
      "checkedInAt": null,
      "createdAt": "2025-12-12T18:02:45.499Z"
    },
    {
      "id": "1765562565504",
      "deskId": "1765561922945",
      "deskName": "A1",
      "locationId": "jhb",
      "date": "2025-12-12",
      "startTime": "08:30",
      "endTime": "09:00",
      "employeeName": "Hugo",
      "employeeEmail": "",
      "checkedIn": false,
      "checkedInAt": null,
      "createdAt": "2025-12-12T18:02:45.504Z"
    },
    {
      "id": "1765562565508",
      "deskId": "1765561922945",
      "deskName": "A1",
      "locationId": "jhb",
      "date": "2025-12-12",
      "startTime": "09:00",
      "endTime": "09:30",
      "employeeName": "Hugo",
      "employeeEmail": "",
      "checkedIn": false,
      "checkedInAt": null,
      "createdAt": "2025-12-12T18:02:45.508Z"
    },
    {
      "id": "1765562565512",
      "deskId": "1765561922945",
      "deskName": "A1",
      "locationId": "jhb",
      "date": "2025-12-12",
      "startTime": "09:30",
      "endTime": "10:00",
      "employeeName": "Hugo",
      "employeeEmail": "",
      "checkedIn": false,
      "checkedInAt": null,
      "createdAt": "2025-12-12T18:02:45.512Z"
    },
    {
      "id": "1765562565516",
      "deskId": "1765561922945",
      "deskName": "A1",
      "locationId": "jhb",
      "date": "2025-12-12",
      "startTime": "10:00",
      "endTime": "10:30",
      "employeeName": "Hugo",
      "employeeEmail": "",
      "checkedIn": false,
      "checkedInAt": null,
      "createdAt": "2025-12-12T18:02:45.516Z"
    },
    {
      "id": "1765562565521",
      "deskId": "1765561922945",
      "deskName": "A1",
      "locationId": "jhb",
      "date": "2025-12-12",
      "startTime": "10:30",
      "endTime": "11:00",
      "employeeName": "Hugo",
      "employeeEmail": "",
      "checkedIn": false,
      "checkedInAt": null,
      "createdAt": "2025-12-12T18:02:45.521Z"
    },
    {
      "id": "1765562565525",
      "deskId": "1765561922945",
      "deskName": "A1",
      "locationId": "jhb",
      "date": "2025-12-12",
      "startTime": "11:00",
      "endTime": "11:30",
      "employeeName": "Hugo",
      "employeeEmail": "",
      "checkedIn": false,
      "checkedInAt": null,
      "createdAt": "2025-12-12T18:02:45.525Z"
    },
    {
      "id": "1765562565529",
      "deskId": "1765561922945",
      "deskName": "A1",
      "locationId": "jhb",
      "date": "2025-12-12",
      "startTime": "11:30",
      "endTime": "12:00",
      "employeeName": "Hugo",
      "employeeEmail": "",
      "checkedIn": false,
      "checkedInAt": null,
      "createdAt": "2025-12-12T18:02:45.529Z"
    },
    {
      "id": "1765562565533",
      "deskId": "1765561922945",
      "deskName": "A1",
      "locationId": "jhb",
      "date": "2025-12-12",
      "startTime": "12:00",
      "endTime": "12:30",
      "employeeName": "Hugo",
      "employeeEmail": "",
      "checkedIn": false,
      "checkedInAt": null,
      "createdAt": "2025-12-12T18:02:45.533Z"
    },
    {
      "id": "1765562657944",
      "deskId": "1765561922945",
      "deskName": "A1",
      "locationId": "jhb",
      "date": "2025-12-13",
      "startTime": "08:00",
      "endTime": "08:30",
      "employeeName": "Hugo",
      "employeeEmail": "",
      "checkedIn": false,
      "checkedInAt": null,
      "createdAt": "2025-12-12T18:04:17.944Z"
    },
    {
      "id": "1765562657949",
      "deskId": "1765561922945",
      "deskName": "A1",
      "locationId": "jhb",
      "date": "2025-12-13",
      "startTime": "08:30",
      "endTime": "09:00",
      "employeeName": "Hugo",
      "employeeEmail": "",
      "checkedIn": false,
      "checkedInAt": null,
      "createdAt": "2025-12-12T18:04:17.949Z"
    },
    {
      "id": "1765562657953",
      "deskId": "1765561922945",
      "deskName": "A1",
      "locationId": "jhb",
      "date": "2025-12-13",
      "startTime": "09:00",
      "endTime": "09:30",
      "employeeName": "Hugo",
      "employeeEmail": "",
      "checkedIn": false,
      "checkedInAt": null,
      "createdAt": "2025-12-12T18:04:17.953Z"
    },
    {
      "id": "1765562657957",
      "deskId": "1765561922945",
      "deskName": "A1",
      "locationId": "jhb",
      "date": "2025-12-13",
      "startTime": "09:30",
      "endTime": "10:00",
      "employeeName": "Hugo",
      "employeeEmail": "",
      "checkedIn": false,
      "checkedInAt": null,
      "createdAt": "2025-12-12T18:04:17.957Z"
    },
    {
      "id": "1765562657961",
      "deskId": "1765561922945",
      "deskName": "A1",
      "locationId": "jhb",
      "date": "2025-12-13",
      "startTime": "10:00",
      "endTime": "10:30",
      "employeeName": "Hugo",
      "employeeEmail": "",
      "checkedIn": false,
      "checkedInAt": null,
      "createdAt": "2025-12-12T18:04:17.961Z"
    },
    {
      "id": "1765562657965",
      "deskId": "1765561922945",
      "deskName": "A1",
      "locationId": "jhb",
      "date": "2025-12-13",
      "startTime": "10:30",
      "endTime": "11:00",
      "employeeName": "Hugo",
      "employeeEmail": "",
      "checkedIn": false,
      "checkedInAt": null,
      "createdAt": "2025-12-12T18:04:17.965Z"
    },
    {
      "id": "1765562657969",
      "deskId": "1765561922945",
      "deskName": "A1",
      "locationId": "jhb",
      "date": "2025-12-13",
      "startTime": "11:00",
      "endTime": "11:30",
      "employeeName": "Hugo",
      "employeeEmail": "",
      "checkedIn": false,
      "checkedInAt": null,
      "createdAt": "2025-12-12T18:04:17.969Z"
    },
    {
      "id": "1765562657973",
      "deskId": "1765561922945",
      "deskName": "A1",
      "locationId": "jhb",
      "date": "2025-12-13",
      "startTime": "11:30",
      "endTime": "12:00",
      "employeeName": "Hugo",
      "employeeEmail": "",
      "checkedIn": false,
      "checkedInAt": null,
      "createdAt": "2025-12-12T18:04:17.973Z"
    },
    {
      "id": "1765562657976",
      "deskId": "1765561922945",
      "deskName": "A1",
      "locationId": "jhb",
      "date": "2025-12-13",
      "startTime": "12:00",
      "endTime": "12:30",
      "employeeName": "Hugo",
      "employeeEmail": "",
      "checkedIn": false,
      "checkedInAt": null,
      "createdAt": "2025-12-12T18:04:17.976Z"
    },
    {
      "id": "1765562657979",
      "deskId": "1765561922945",
      "deskName": "A1",
      "locationId": "jhb",
      "date": "2025-12-13",
      "startTime": "12:30",
      "endTime": "13:00",
      "employeeName": "Hugo",
      "employeeEmail": "",
      "checkedIn": false,
      "checkedInAt": null,
      "createdAt": "2025-12-12T18:04:17.979Z"
    },
    {
      "id": "1765562657982",
      "deskId": "1765561922945",
      "deskName": "A1",
      "locationId": "jhb",
      "date": "2025-12-13",
      "startTime": "13:00",
      "endTime": "13:30",
      "employeeName": "Hugo",
      "employeeEmail": "",
      "checkedIn": false,
      "checkedInAt": null,
      "createdAt": "2025-12-12T18:04:17.982Z"
    },
    {
      "id": "1765562657985",
      "deskId": "1765561922945",
      "deskName": "A1",
      "locationId": "jhb",
      "date": "2025-12-13",
      "startTime": "13:30",
      "endTime": "14:00",
      "employeeName": "Hugo",
      "employeeEmail": "",
      "checkedIn": false,
      "checkedInAt": null,
      "createdAt": "2025-12-12T18:04:17.985Z"
    },
    {
      "id": "1765562657989",
      "deskId": "1765561922945",
      "deskName": "A1",
      "locationId": "jhb",
      "date": "2025-12-13",
      "startTime": "14:00",
      "endTime": "14:30",
      "employeeName": "Hugo",
      "employeeEmail": "",
      "checkedIn": false,
      "checkedInAt": null,
      "createdAt": "2025-12-12T18:04:17.989Z"
    },
    {
      "id": "1765562657992",
      "deskId": "1765561922945",
      "deskName": "A1",
      "locationId": "jhb",
      "date": "2025-12-13",
      "startTime": "14:30",
      "endTime": "15:00",
      "employeeName": "Hugo",
      "employeeEmail": "",
      "checkedIn": false,
      "checkedInAt": null,
      "createdAt": "2025-12-12T18:04:17.992Z"
    },
    {
      "id": "1765562657995",
      "deskId": "1765561922945",
      "deskName": "A1",
      "locationId": "jhb",
      "date": "2025-12-13",
      "startTime": "15:00",
      "endTime": "15:30",
      "employeeName": "Hugo",
      "employeeEmail": "",
      "checkedIn": false,
      "checkedInAt": null,
      "createdAt": "2025-12-12T18:04:17.995Z"
    },
    {
      "id": "1765562657999",
      "deskId": "1765561922945",
      "deskName": "A1",
      "locationId": "jhb",
      "date": "2025-12-13",
      "startTime": "15:30",
      "endTime": "16:00",
      "employeeName": "Hugo",
      "employeeEmail": "",
      "checkedIn": false,
      "checkedInAt": null,
      "createdAt": "2025-12-12T18:04:17.999Z"
    },
    {
      "id": "1765562669505",
      "deskId": "1765561922945",
      "deskName": "A1",
      "locationId": "jhb",
      "date": "2025-12-13",
      "startTime": "16:00",
      "endTime": "16:30",
      "employeeName": "Michelle",
      "employeeEmail": "",
      "checkedIn": false,
      "checkedInAt": null,
      "createdAt": "2025-12-12T18:04:29.505Z"
    },
    {
      "id": "1765562669510",
      "deskId": "1765561922945",
      "deskName": "A1",
      "locationId": "jhb",
      "date": "2025-12-13",
      "startTime": "16:30",
      "endTime": "17:00",
      "employeeName": "Michelle",
      "employeeEmail": "",
      "checkedIn": false,
      "checkedInAt": null,
      "createdAt": "2025-12-12T18:04:29.510Z"
    },
    {
      "id": "1765565687756",
      "deskId": "1765565073508",
      "deskName": "A01",
      "locationId": "jhb",
      "date": "2025-12-16",
      "startTime": "00:00",
      "endTime": "00:30",
      "employeeName": "Michelle",
      "employeeEmail": "",
      "teamId": null,
      "checkedIn": false,
      "checkedInAt": null,
      "createdAt": "2025-12-12T18:54:47.756Z"
    },
    {
      "id": "1765565687762",
      "deskId": "1765565073508",
      "deskName": "A01",
      "locationId": "jhb",
      "date": "2025-12-16",
      "startTime": "00:30",
      "endTime": "01:00",
      "employeeName": "Michelle",
      "employeeEmail": "",
      "teamId": null,
      "checkedIn": false,
      "checkedInAt": null,
      "createdAt": "2025-12-12T18:54:47.762Z"
    },
    {
      "id": "1765565687766",
      "deskId": "1765565073508",
      "deskName": "A01",
      "locationId": "jhb",
      "date": "2025-12-16",
      "startTime": "01:00",
      "endTime": "01:30",
      "employeeName": "Michelle",
      "employeeEmail": "",
      "teamId": null,
      "checkedIn": false,
      "checkedInAt": null,
      "createdAt": "2025-12-12T18:54:47.766Z"
    },
    {
      "id": "1765565687770",
      "deskId": "1765565073508",
      "deskName": "A01",
      "locationId": "jhb",
      "date": "2025-12-16",
      "startTime": "01:30",
      "endTime": "02:00",
      "employeeName": "Michelle",
      "employeeEmail": "",
      "teamId": null,
      "checkedIn": false,
      "checkedInAt": null,
      "createdAt": "2025-12-12T18:54:47.770Z"
    },
    {
      "id": "1765565687774",
      "deskId": "1765565073508",
      "deskName": "A01",
      "locationId": "jhb",
      "date": "2025-12-16",
      "startTime": "02:00",
      "endTime": "02:30",
      "employeeName": "Michelle",
      "employeeEmail": "",
      "teamId": null,
      "checkedIn": false,
      "checkedInAt": null,
      "createdAt": "2025-12-12T18:54:47.774Z"
    },
    {
      "id": "1765565687778",
      "deskId": "1765565073508",
      "deskName": "A01",
      "locationId": "jhb",
      "date": "2025-12-16",
      "startTime": "02:30",
      "endTime": "03:00",
      "employeeName": "Michelle",
      "employeeEmail": "",
      "teamId": null,
      "checkedIn": false,
      "checkedInAt": null,
      "createdAt": "2025-12-12T18:54:47.778Z"
    },
    {
      "id": "1765565687782",
      "deskId": "1765565073508",
      "deskName": "A01",
      "locationId": "jhb",
      "date": "2025-12-16",
      "startTime": "03:00",
      "endTime": "03:30",
      "employeeName": "Michelle",
      "employeeEmail": "",
      "teamId": null,
      "checkedIn": false,
      "checkedInAt": null,
      "createdAt": "2025-12-12T18:54:47.782Z"
    },
    {
      "id": "1765565687785",
      "deskId": "1765565073508",
      "deskName": "A01",
      "locationId": "jhb",
      "date": "2025-12-16",
      "startTime": "03:30",
      "endTime": "04:00",
      "employeeName": "Michelle",
      "employeeEmail": "",
      "teamId": null,
      "checkedIn": false,
      "checkedInAt": null,
      "createdAt": "2025-12-12T18:54:47.785Z"
    },
    {
      "id": "1765565687788",
      "deskId": "1765565073508",
      "deskName": "A01",
      "locationId": "jhb",
      "date": "2025-12-16",
      "startTime": "04:00",
      "endTime": "04:30",
      "employeeName": "Michelle",
      "employeeEmail": "",
      "teamId": null,
      "checkedIn": false,
      "checkedInAt": null,
      "createdAt": "2025-12-12T18:54:47.788Z"
    },
    {
      "id": "1765565687792",
      "deskId": "1765565073508",
      "deskName": "A01",
      "locationId": "jhb",
      "date": "2025-12-16",
      "startTime": "04:30",
      "endTime": "05:00",
      "employeeName": "Michelle",
      "employeeEmail": "",
      "teamId": null,
      "checkedIn": false,
      "checkedInAt": null,
      "createdAt": "2025-12-12T18:54:47.792Z"
    },
    {
      "id": "1765565687795",
      "deskId": "1765565073508",
      "deskName": "A01",
      "locationId": "jhb",
      "date": "2025-12-16",
      "startTime": "05:00",
      "endTime": "05:30",
      "employeeName": "Michelle",
      "employeeEmail": "",
      "teamId": null,
      "checkedIn": false,
      "checkedInAt": null,
      "createdAt": "2025-12-12T18:54:47.795Z"
    },
    {
      "id": "1765565687799",
      "deskId": "1765565073508",
      "deskName": "A01",
      "locationId": "jhb",
      "date": "2025-12-16",
      "startTime": "05:30",
      "endTime": "06:00",
      "employeeName": "Michelle",
      "employeeEmail": "",
      "teamId": null,
      "checkedIn": false,
      "checkedInAt": null,
      "createdAt": "2025-12-12T18:54:47.799Z"
    },
    {
      "id": "1765565687802",
      "deskId": "1765565073508",
      "deskName": "A01",
      "locationId": "jhb",
      "date": "2025-12-16",
      "startTime": "06:00",
      "endTime": "06:30",
      "employeeName": "Michelle",
      "employeeEmail": "",
      "teamId": null,
      "checkedIn": false,
      "checkedInAt": null,
      "createdAt": "2025-12-12T18:54:47.802Z"
    },
    {
      "id": "1765565687806",
      "deskId": "1765565073508",
      "deskName": "A01",
      "locationId": "jhb",
      "date": "2025-12-16",
      "startTime": "06:30",
      "endTime": "07:00",
      "employeeName": "Michelle",
      "employeeEmail": "",
      "teamId": null,
      "checkedIn": false,
      "checkedInAt": null,
      "createdAt": "2025-12-12T18:54:47.806Z"
    },
    {
      "id": "1765565687810",
      "deskId": "1765565073508",
      "deskName": "A01",
      "locationId": "jhb",
      "date": "2025-12-16",
      "startTime": "07:00",
      "endTime": "07:30",
      "employeeName": "Michelle",
      "employeeEmail": "",
      "teamId": null,
      "checkedIn": false,
      "checkedInAt": null,
      "createdAt": "2025-12-12T18:54:47.810Z"
    },
    {
      "id": "1765565687814",
      "deskId": "1765565073508",
      "deskName": "A01",
      "locationId": "jhb",
      "date": "2025-12-16",
      "startTime": "07:30",
      "endTime": "08:00",
      "employeeName": "Michelle",
      "employeeEmail": "",
      "teamId": null,
      "checkedIn": false,
      "checkedInAt": null,
      "createdAt": "2025-12-12T18:54:47.814Z"
    },
    {
      "id": "1765565687818",
      "deskId": "1765565073508",
      "deskName": "A01",
      "locationId": "jhb",
      "date": "2025-12-16",
      "startTime": "08:00",
      "endTime": "08:30",
      "employeeName": "Michelle",
      "employeeEmail": "",
      "teamId": null,
      "checkedIn": false,
      "checkedInAt": null,
      "createdAt": "2025-12-12T18:54:47.818Z"
    },
    {
      "id": "1765565687822",
      "deskId": "1765565073508",
      "deskName": "A01",
      "locationId": "jhb",
      "date": "2025-12-16",
      "startTime": "08:30",
      "endTime": "09:00",
      "employeeName": "Michelle",
      "employeeEmail": "",
      "teamId": null,
      "checkedIn": false,
      "checkedInAt": null,
      "createdAt": "2025-12-12T18:54:47.822Z"
    },
    {
      "id": "1765565687826",
      "deskId": "1765565073508",
      "deskName": "A01",
      "locationId": "jhb",
      "date": "2025-12-16",
      "startTime": "09:00",
      "endTime": "09:30",
      "employeeName": "Michelle",
      "employeeEmail": "",
      "teamId": null,
      "checkedIn": false,
      "checkedInAt": null,
      "createdAt": "2025-12-12T18:54:47.826Z"
    },
    {
      "id": "1765565687830",
      "deskId": "1765565073508",
      "deskName": "A01",
      "locationId": "jhb",
      "date": "2025-12-16",
      "startTime": "09:30",
      "endTime": "10:00",
      "employeeName": "Michelle",
      "employeeEmail": "",
      "teamId": null,
      "checkedIn": false,
      "checkedInAt": null,
      "createdAt": "2025-12-12T18:54:47.830Z"
    },
    {
      "id": "1765565687834",
      "deskId": "1765565073508",
      "deskName": "A01",
      "locationId": "jhb",
      "date": "2025-12-16",
      "startTime": "10:00",
      "endTime": "10:30",
      "employeeName": "Michelle",
      "employeeEmail": "",
      "teamId": null,
      "checkedIn": false,
      "checkedInAt": null,
      "createdAt": "2025-12-12T18:54:47.834Z"
    },
    {
      "id": "1765565687838",
      "deskId": "1765565073508",
      "deskName": "A01",
      "locationId": "jhb",
      "date": "2025-12-16",
      "startTime": "10:30",
      "endTime": "11:00",
      "employeeName": "Michelle",
      "employeeEmail": "",
      "teamId": null,
      "checkedIn": false,
      "checkedInAt": null,
      "createdAt": "2025-12-12T18:54:47.838Z"
    },
    {
      "id": "1765565687842",
      "deskId": "1765565073508",
      "deskName": "A01",
      "locationId": "jhb",
      "date": "2025-12-16",
      "startTime": "11:00",
      "endTime": "11:30",
      "employeeName": "Michelle",
      "employeeEmail": "",
      "teamId": null,
      "checkedIn": false,
      "checkedInAt": null,
      "createdAt": "2025-12-12T18:54:47.842Z"
    },
    {
      "id": "1765565687846",
      "deskId": "1765565073508",
      "deskName": "A01",
      "locationId": "jhb",
      "date": "2025-12-16",
      "startTime": "11:30",
      "endTime": "12:00",
      "employeeName": "Michelle",
      "employeeEmail": "",
      "teamId": null,
      "checkedIn": false,
      "checkedInAt": null,
      "createdAt": "2025-12-12T18:54:47.846Z"
    },
    {
      "id": "1765565687850",
      "deskId": "1765565073508",
      "deskName": "A01",
      "locationId": "jhb",
      "date": "2025-12-16",
      "startTime": "12:00",
      "endTime": "12:30",
      "employeeName": "Michelle",
      "employeeEmail": "",
      "teamId": null,
      "checkedIn": false,
      "checkedInAt": null,
      "createdAt": "2025-12-12T18:54:47.850Z"
    },
    {
      "id": "1765565687853",
      "deskId": "1765565073508",
      "deskName": "A01",
      "locationId": "jhb",
      "date": "2025-12-16",
      "startTime": "12:30",
      "endTime": "13:00",
      "employeeName": "Michelle",
      "employeeEmail": "",
      "teamId": null,
      "checkedIn": false,
      "checkedInAt": null,
      "createdAt": "2025-12-12T18:54:47.853Z"
    },
    {
      "id": "1765565687858",
      "deskId": "1765565073508",
      "deskName": "A01",
      "locationId": "jhb",
      "date": "2025-12-16",
      "startTime": "13:00",
      "endTime": "13:30",
      "employeeName": "Michelle",
      "employeeEmail": "",
      "teamId": null,
      "checkedIn": false,
      "checkedInAt": null,
      "createdAt": "2025-12-12T18:54:47.858Z"
    },
    {
      "id": "1765565687862",
      "deskId": "1765565073508",
      "deskName": "A01",
      "locationId": "jhb",
      "date": "2025-12-16",
      "startTime": "13:30",
      "endTime": "14:00",
      "employeeName": "Michelle",
      "employeeEmail": "",
      "teamId": null,
      "checkedIn": false,
      "checkedInAt": null,
      "createdAt": "2025-12-12T18:54:47.862Z"
    },
    {
      "id": "1765565687866",
      "deskId": "1765565073508",
      "deskName": "A01",
      "locationId": "jhb",
      "date": "2025-12-16",
      "startTime": "14:00",
      "endTime": "14:30",
      "employeeName": "Michelle",
      "employeeEmail": "",
      "teamId": null,
      "checkedIn": false,
      "checkedInAt": null,
      "createdAt": "2025-12-12T18:54:47.866Z"
    },
    {
      "id": "1765565687869",
      "deskId": "1765565073508",
      "deskName": "A01",
      "locationId": "jhb",
      "date": "2025-12-16",
      "startTime": "14:30",
      "endTime": "15:00",
      "employeeName": "Michelle",
      "employeeEmail": "",
      "teamId": null,
      "checkedIn": false,
      "checkedInAt": null,
      "createdAt": "2025-12-12T18:54:47.869Z"
    },
    {
      "id": "1765565687873",
      "deskId": "1765565073508",
      "deskName": "A01",
      "locationId": "jhb",
      "date": "2025-12-16",
      "startTime": "15:00",
      "endTime": "15:30",
      "employeeName": "Michelle",
      "employeeEmail": "",
      "teamId": null,
      "checkedIn": false,
      "checkedInAt": null,
      "createdAt": "2025-12-12T18:54:47.873Z"
    },
    {
      "id": "1765565687877",
      "deskId": "1765565073508",
      "deskName": "A01",
      "locationId": "jhb",
      "date": "2025-12-16",
      "startTime": "15:30",
      "endTime": "16:00",
      "employeeName": "Michelle",
      "employeeEmail": "",
      "teamId": null,
      "checkedIn": false,
      "checkedInAt": null,
      "createdAt": "2025-12-12T18:54:47.877Z"
    },
    {
      "id": "1765565687880",
      "deskId": "1765565073508",
      "deskName": "A01",
      "locationId": "jhb",
      "date": "2025-12-16",
      "startTime": "16:00",
      "endTime": "16:30",
      "employeeName": "Michelle",
      "employeeEmail": "",
      "teamId": null,
      "checkedIn": false,
      "checkedInAt": null,
      "createdAt": "2025-12-12T18:54:47.880Z"
    },
    {
      "id": "1765565687883",
      "deskId": "1765565073508",
      "deskName": "A01",
      "locationId": "jhb",
      "date": "2025-12-16",
      "startTime": "16:30",
      "endTime": "17:00",
      "employeeName": "Michelle",
      "employeeEmail": "",
      "teamId": null,
      "checkedIn": false,
      "checkedInAt": null,
      "createdAt": "2025-12-12T18:54:47.883Z"
    },
    {
      "id": "1765565687887",
      "deskId": "1765565073508",
      "deskName": "A01",
      "locationId": "jhb",
      "date": "2025-12-16",
      "startTime": "17:00",
      "endTime": "17:30",
      "employeeName": "Michelle",
      "employeeEmail": "",
      "teamId": null,
      "checkedIn": false,
      "checkedInAt": null,
      "createdAt": "2025-12-12T18:54:47.887Z"
    },
    {
      "id": "1765565687890",
      "deskId": "1765565073508",
      "deskName": "A01",
      "locationId": "jhb",
      "date": "2025-12-16",
      "startTime": "17:30",
      "endTime": "18:00",
      "employeeName": "Michelle",
      "employeeEmail": "",
      "teamId": null,
      "checkedIn": false,
      "checkedInAt": null,
      "createdAt": "2025-12-12T18:54:47.890Z"
    }
  ],
  "floorElements": [
    {
      "id": "1765564351159",
      "type": "room",
      "locationId": "jhb",
      "floor": "1",
      "x": 0,
      "y": 0,
      "width": 210,
      "height": 160,
      "points": [],
      "label": "Meeting",
      "color": "#3b82f6",
      "createdAt": "2025-12-12T18:32:31.159Z"
    },
    {
      "id": "1765564835805",
      "type": "room",
      "locationId": "jhb",
      "floor": "1",
      "x": 210,
      "y": 0,
      "width": 60,
      "height": 100,
      "points": [],
      "label": "Store room",
      "color": "#3b82f6",
      "createdAt": "2025-12-12T18:40:35.805Z"
    },
    {
      "id": "1765564949509",
      "type": "room",
      "locationId": "jhb",
      "floor": "1",
      "x": 270,
      "y": 0,
      "width": 210,
      "height": 100,
      "points": [],
      "label": "Finance",
      "color": "#3b82f6",
      "createdAt": "2025-12-12T18:42:29.509Z"
    }
  ]
}